[
  {
    "CdsFCBContext": "{\"FileType\":true,\"ImageExternalStorage\":true}",
    "EntitySetName": "contoso_prioritztopics",
    "IsHidden": false,
    "IsSampleData": false,
    "IsWritable": true,
    "LogicalName": "contoso_prioritztopic",
    "MaxGetRowsCount": 500,
    "Name": "Prioritz Topics",
    "NativeCDSDataSourceInfoNameMapping": {
      "_ownerid_value": "Owner",
      "contoso_details": "Details",
      "contoso_photo": "Photo",
      "contoso_photoid": "contoso_PhotoId",
      "contoso_prioritztopic_AsyncOperations": "System Jobs",
      "contoso_prioritztopic_BulkDeleteFailures": "Bulk Delete Failures",
      "contoso_prioritztopic_DuplicateBaseRecord": "Duplicate Records (contoso_prioritztopic_DuplicateBaseRecord)",
      "contoso_prioritztopic_DuplicateMatchingRecord": "Duplicate Records (contoso_prioritztopic_DuplicateMatchingRecord)",
      "contoso_prioritztopic_MailboxTrackingFolders": "Mailbox Auto Tracking Folders",
      "contoso_prioritztopic_PrincipalObjectAttributeAccesses": "Field Sharing",
      "contoso_PrioritzTopic_PrioritzTopicItem": "PrioritZ Topic Items",
      "contoso_PrioritzTopic_PrioritzTopicParticipant": "PrioritZ Topic Participants",
      "contoso_prioritztopic_ProcessSession": "Process Sessions",
      "contoso_prioritztopic_SyncErrors": "Sync Errors",
      "contoso_prioritztopicid": "PrioritZ Topic",
      "contoso_respondby": "Respond By",
      "contoso_topic": "Topic",
      "createdby": "Created By",
      "createdon": "Created On",
      "createdonbehalfby": "Created By (Delegate)",
      "importsequencenumber": "Import Sequence Number",
      "modifiedby": "Modified By",
      "modifiedon": "Modified On",
      "modifiedonbehalfby": "Modified By (Delegate)",
      "overriddencreatedon": "Record Created On",
      "owningbusinessunit": "Owning Business Unit",
      "owningteam": "Owning Team",
      "owninguser": "Owning User",
      "statecode": "Status",
      "statuscode": "Status Reason",
      "timezoneruleversionnumber": "Time Zone Rule Version Number",
      "utcconversiontimezonecode": "UTC Conversion Time Zone Code",
      "versionnumber": "Version Number"
    },
    "PreferredName": "Prioritz Topics",
    "Type": "NativeCDSDataSourceInfo"
  },
  {
    "DisplayName": "Prioritz Topics (Views)",
    "Name": "_contoso_prioritztopic_views",
    "RelatedEntityName": "Prioritz Topics",
    "TrimmedViewName": true,
    "Type": "ViewInfo",
    "ViewInfoNameMapping": {
      "3c831c2b-9c3e-49c5-b3ad-be3f9d1b50ce": "Active Prioritz Topics",
      "551bc2b4-fb4b-4bf1-b370-439dfbeafe6a": "Prioritz Topic Advanced Find View",
      "6cb61b40-573a-4982-aa98-90cbfc055e78": "Prioritz Topic Associated View",
      "b7bb7a05-1af8-4bde-9d5d-2f9f63332ae8": "Inactive Prioritz Topics",
      "f618cd5f-34e3-46cf-8fde-b3884ce529b0": "Prioritz Topic Lookup View"
    }
  },
  {
    "DisplayName": "Status (Prioritz Topics)",
    "Name": "contoso_prioritztopic_statecode",
    "OptionSetInfoNameMapping": {
      "0": "Active",
      "1": "Inactive"
    },
    "OptionSetIsBooleanValued": false,
    "OptionSetIsGlobal": false,
    "OptionSetReference": {
      "OptionSetReferenceItem0": {
        "OptionSetReferenceColumnName": "statecode",
        "OptionSetReferenceEntityName": "Prioritz Topics"
      }
    },
    "OptionSetTypeKey": "StateType",
    "RelatedColumnInvariantName": "statecode",
    "RelatedEntityName": "Prioritz Topics",
    "Type": "OptionSetInfo"
  },
  {
    "DisplayName": "Status Reason (Prioritz Topics)",
    "Name": "contoso_prioritztopic_statuscode",
    "OptionSetInfoNameMapping": {
      "1": "Active",
      "2": "Inactive"
    },
    "OptionSetIsBooleanValued": false,
    "OptionSetIsGlobal": false,
    "OptionSetReference": {
      "OptionSetReferenceItem0": {
        "OptionSetReferenceColumnName": "statuscode",
        "OptionSetReferenceEntityName": "Prioritz Topics"
      }
    },
    "OptionSetTypeKey": "StatusType",
    "RelatedColumnInvariantName": "statuscode",
    "RelatedEntityName": "Prioritz Topics",
    "Type": "OptionSetInfo"
  }
]